pyproject.toml
setup.py
distributed_compy/__init__.py
distributed_compy.egg-info/PKG-INFO
distributed_compy.egg-info/SOURCES.txt
distributed_compy.egg-info/dependency_links.txt
distributed_compy.egg-info/not-zip-safe
distributed_compy.egg-info/top_level.txt
distributed_compy/_config/__init__.py
distributed_compy/_config/_local/ConfigureLocal.cpp
distributed_compy/_config/_local/GetGPUBands.cu
distributed_compy/_config/_local/GetLocalBands.cpp
distributed_compy/_config/_local/SetLocalBands.cpp
distributed_compy/_config/_local/_configure_local.cpp
distributed_compy/_config/_local/_get_local_bands.cpp
distributed_compy/_config/_network/ConfigureNetwork.cpp
distributed_compy/_config/_network/_configure_network.cpp
distributed_compy/_include/__init__.py
distributed_compy/_include/_config/ConfigureLocal.h
distributed_compy/_include/_config/ConfigureNetwork.h
distributed_compy/_include/_config/GetGPUBands.h
distributed_compy/_include/_config/GetLocalBands.h
distributed_compy/_include/_config/SetLocalBands.h
distributed_compy/_include/_config/__init__.py
distributed_compy/_include/_lib/GPUReductionSum.h
distributed_compy/_include/_lib/HeteroReductionSum.h
distributed_compy/_include/_lib/HybridReductionSum.h
distributed_compy/_include/_lib/NaiveSum.h
distributed_compy/_include/_lib/OMPReductionSum.h
distributed_compy/_include/_lib/__init__.py
distributed_compy/_include/_util/DataExtractor.h
distributed_compy/_include/_util/GetFileLen.h
distributed_compy/_include/_util/LoadBalancer.h
distributed_compy/_include/_util/__init__.py
distributed_compy/_lib/__init__.py
distributed_compy/_lib/_gpu_reduction_sum/GPUReductionSum.cu
distributed_compy/_lib/_gpu_reduction_sum/_gpu_reduction_sum.cpp
distributed_compy/_lib/_hetero_reduction_sum/HeteroReductionSum.cpp
distributed_compy/_lib/_hetero_reduction_sum/_hetero_reduction_sum.cpp
distributed_compy/_lib/_hybrid_reduction_sum/HybridReductionSum.cpp
distributed_compy/_lib/_hybrid_reduction_sum/_hybrid_reduction_sum.cpp
distributed_compy/_lib/_naive_sum/NaiveSum.cpp
distributed_compy/_lib/_naive_sum/_naive_sum.cpp
distributed_compy/_lib/_omp_reduction_sum/OMPReductionSum.cpp
