Metadata-Version: 2.1
Name: distributed-compy
Version: 1.0.44
Summary: Distributed hybrid (multi-node) heterogeneous (CPU + multi-GPU) computing library. Utilizes and requires CUDA toolkit, OpenMP, and OpenMPI.
Author: Logan Nelsen
Author-email: 1nel.logan1@gmail.com
License: MIT
Classifier: Development Status :: 5 - Production/Stable
Classifier: Environment :: GPU :: NVIDIA CUDA
Classifier: Intended Audience :: Developers
Classifier: Intended Audience :: Science/Research
Classifier: Intended Audience :: System Administrators
Classifier: Intended Audience :: End Users/Desktop
Classifier: License :: OSI Approved :: MIT License
Classifier: Operating System :: POSIX
Classifier: Programming Language :: C++
Classifier: Programming Language :: Cython
Classifier: Programming Language :: Python
Classifier: Topic :: Scientific/Engineering
Classifier: Topic :: System :: Clustering
Classifier: Topic :: System :: Distributed Computing
Classifier: Topic :: Software Development
Classifier: Topic :: Software Development :: Code Generators
Classifier: Topic :: Utilities
